bkbit/LICENSE
bkbit/__init__.py
bkbit/_version.py
bkbit/cli.py
bkbit/data_translators/README.md
bkbit/data_translators/__init__.py
bkbit/data_translators/anatomical_structure_translator.py
bkbit/data_translators/genome_annotation_translator.py
bkbit/data_translators/libray_generation_translator.py
bkbit/model_converters/README.md
bkbit/model_converters/__init__.py
bkbit/model_converters/sheets_converter.py
bkbit/model_editors/README.md
bkbit/model_editors/__init__.py
bkbit/model_editors/add_dunderMethods_genomeAnnotation.py
bkbit/model_editors/linkml_trimmer.py
bkbit/models/__init__.py
bkbit/models/anatomical_structure.py
bkbit/models/genome_annotation.py
bkbit/models/library_generation.py
bkbit/tests/test_ga_translator_ensembl.py
bkbit/tests/test_ga_translator_ncbi.py
bkbit/tests/test_specimen_portal_translator.py
bkbit/utils/__init__.py
bkbit/utils/bican_to_nimp_slots.csv
bkbit-0.1.1.dist-info/LICENSE
bkbit-0.1.1.dist-info/METADATA
bkbit-0.1.1.dist-info/WHEEL
bkbit-0.1.1.dist-info/entry_points.txt
bkbit-0.1.1.dist-info/top_level.txt
bkbit-0.1.1.dist-info/RECORD
