Metadata-Version: 2.1
Name: bkbit
Version: 0.1.1
Summary: A library for atlaskb data models
Author: bkbit developers
License: Apache 2.0
Project-URL: Homepage, https://github.com/atlaskb/bkbit
Classifier: Programming Language :: Python :: 3
Classifier: Operating System :: OS Independent
Requires-Python: >=3.7
License-File: LICENSE
Requires-Dist: linkml >=1.5
Requires-Dist: pandas
Requires-Dist: click
Requires-Dist: schemasheets
Provides-Extra: docs
Requires-Dist: mkdocs-material ; extra == 'docs'
Provides-Extra: test
Requires-Dist: pytest ; extra == 'test'
